seating/__init__.py
seating/py.typed
seating/seating.py
seating-0.0.3.dist-info/METADATA
seating-0.0.3.dist-info/WHEEL
seating-0.0.3.dist-info/entry_points.txt
seating-0.0.3.dist-info/licenses/LICENSE.txt
seating-0.0.3.dist-info/RECORD
