Metadata-Version: 2.1
Name: seating
Version: 0.0.3
Summary: Sort the order of class functions and properties
Project-URL: Homepage, https://github.com/matt-manes/seating
Project-URL: Documentation, https://github.com/matt-manes/seating/tree/main/docs
Project-URL: Source code, https://github.com/matt-manes/seating/tree/main/src/seating
Author-email: Matt Manes <mattmanes@pm.me>
License-File: LICENSE.txt
Keywords: alphabetical,order,sort,style
Classifier: License :: OSI Approved :: MIT License
Classifier: Operating System :: OS Independent
Classifier: Programming Language :: Python :: 3
Requires-Python: >=3.10
Requires-Dist: ast-comments
Requires-Dist: black
Requires-Dist: pathier
Requires-Dist: pytest
